[
  {
    "order_id": 1,
    "course_id": 3,
    "period": 1
  },
  {
    "order_id": 1,
    "course_id": 6,
    "period": 1
  },
  {
    "order_id": 1,
    "course_id": 9,
    "period": 1
  },
  {
    "order_id": 2,
    "course_id": 6,
    "period": 1
  },
  {
    "order_id": 2,
    "course_id": 10,
    "period": 1
  },
  {
    "order_id": 2,
    "course_id": 12,
    "period": 1
  },
  {
    "order_id": 3,
    "course_id": 33,
    "period": 1
  },
  {
    "order_id": 3,
    "course_id": 44,
    "period": 1
  },
  {
    "order_id": 3,
    "course_id": 55,
    "period": 1
  },
  {
    "order_id": 4,
    "course_id": 65,
    "period": 1
  },
  {
    "order_id": 4,
    "course_id": 62,
    "period": 1
  },
  {
    "order_id": 4,
    "course_id": 3,
    "period": 1
  }
]