[
    {"detail_id":"1316","order_id":"800dd514-4d22-4a2b-b290-35fc43bc45e1","product_id":"4","top":"0","left":"0","z_index":"0","rotate":"0","created_at":"2024-05-03 12:02:46","updated_at":"2024-05-03 12:02:46"},
    {"detail_id":"1317","order_id":"800dd514-4d22-4a2b-b290-35fc43bc45e1","product_id":"31","top":"0","left":"0","z_index":"0","rotate":"0","created_at":"2024-05-03 12:02:46","updated_at":"2024-05-03 12:02:46"},
    {"detail_id":"1318","order_id":"800dd514-4d22-4a2b-b290-35fc43bc45e1","product_id":"31","top":"-7","left":"25","z_index":"0","rotate":"0","created_at":"2024-05-03 12:02:46","updated_at":"2024-05-03 12:02:46"},
    {"detail_id":"1319","order_id":"800dd514-4d22-4a2b-b290-35fc43bc45e1","product_id":"30","top":"1","left":"130","z_index":"0","rotate":"0","created_at":"2024-05-03 12:02:46","updated_at":"2024-05-03 12:02:46"},
    {"detail_id":"1320","order_id":"800dd514-4d22-4a2b-b290-35fc43bc45e1","product_id":"30","top":"0","left":"0","z_index":"0","rotate":"0","created_at":"2024-05-03 12:02:46","updated_at":"2024-05-03 12:02:46"},
    {"detail_id":"1321","order_id":"92d41d15-ce0c-4253-a645-d173e05aab01","product_id":"2","top":"0","left":"0","z_index":"0","rotate":"0","created_at":"2024-05-03 12:04:10","updated_at":"2024-05-03 12:04:10"},
    {"detail_id":"1322","order_id":"92d41d15-ce0c-4253-a645-d173e05aab01","product_id":"3","top":"0","left":"0","z_index":"0","rotate":"0","created_at":"2024-05-03 12:04:10","updated_at":"2024-05-03 12:04:10"},
    {"detail_id":"1323","order_id":"92d41d15-ce0c-4253-a645-d173e05aab01","product_id":"4","top":"0","left":"0","z_index":"0","rotate":"0","created_at":"2024-05-03 12:04:10","updated_at":"2024-05-03 12:04:10"},
    {"detail_id":"1324","order_id":"92d41d15-ce0c-4253-a645-d173e05aab01","product_id":"2","top":"0","left":"0","z_index":"0","rotate":"0","created_at":"2024-05-03 12:04:10","updated_at":"2024-05-03 12:04:10"},
    {"detail_id":"1325","order_id":"92d41d15-ce0c-4253-a645-d173e05aab01","product_id":"3","top":"0","left":"0","z_index":"0","rotate":"0","created_at":"2024-05-03 12:04:10","updated_at":"2024-05-03 12:04:10"},
    {"detail_id":"1326","order_id":"92d41d15-ce0c-4253-a645-d173e05aab01","product_id":"4","top":"0","left":"0","z_index":"0","rotate":"0","created_at":"2024-05-03 12:04:10","updated_at":"2024-05-03 12:04:10"},
    {"detail_id":"1327","order_id":"92d41d15-ce0c-4253-a645-d173e05aab01","product_id":"31","top":"0","left":"0","z_index":"0","rotate":"0","created_at":"2024-05-03 12:04:10","updated_at":"2024-05-03 12:04:10"},
    {"detail_id":"1328","order_id":"92d41d15-ce0c-4253-a645-d173e05aab01","product_id":"31","top":"-7","left":"25","z_index":"0","rotate":"0","created_at":"2024-05-03 12:04:10","updated_at":"2024-05-03 12:04:10"},
    {"detail_id":"1329","order_id":"92d41d15-ce0c-4253-a645-d173e05aab01","product_id":"30","top":"1","left":"130","z_index":"0","rotate":"0","created_at":"2024-05-03 12:04:10","updated_at":"2024-05-03 12:04:10"},
    {"detail_id":"1330","order_id":"92d41d15-ce0c-4253-a645-d173e05aab01","product_id":"30","top":"0","left":"0","z_index":"0","rotate":"0","created_at":"2024-05-03 12:04:10","updated_at":"2024-05-03 12:04:10"},
    {"detail_id":"1331","order_id":"9e93f233-7bf7-4114-96f9-d7333eb42d47","product_id":"2","top":"0","left":"0","z_index":"0","rotate":"0","created_at":"2024-05-03 12:05:25","updated_at":"2024-05-03 12:05:25"},
    {"detail_id":"1332","order_id":"9e93f233-7bf7-4114-96f9-d7333eb42d47","product_id":"3","top":"0","left":"0","z_index":"0","rotate":"0","created_at":"2024-05-03 12:05:25","updated_at":"2024-05-03 12:05:25"},
    {"detail_id":"1333","order_id":"9e93f233-7bf7-4114-96f9-d7333eb42d47","product_id":"4","top":"0","left":"0","z_index":"0","rotate":"0","created_at":"2024-05-03 12:05:25","updated_at":"2024-05-03 12:05:25"},
    {"detail_id":"1334","order_id":"9e93f233-7bf7-4114-96f9-d7333eb42d47","product_id":"2","top":"0","left":"0","z_index":"0","rotate":"0","created_at":"2024-05-03 12:05:25","updated_at":"2024-05-03 12:05:25"},
    {"detail_id":"1335","order_id":"9e93f233-7bf7-4114-96f9-d7333eb42d47","product_id":"3","top":"0","left":"0","z_index":"0","rotate":"0","created_at":"2024-05-03 12:05:25","updated_at":"2024-05-03 12:05:25"},
    {"detail_id":"1336","order_id":"9e93f233-7bf7-4114-96f9-d7333eb42d47","product_id":"4","top":"0","left":"0","z_index":"0","rotate":"0","created_at":"2024-05-03 12:05:25","updated_at":"2024-05-03 12:05:25"},
    {"detail_id":"1337","order_id":"9e93f233-7bf7-4114-96f9-d7333eb42d47","product_id":"31","top":"0","left":"0","z_index":"0","rotate":"0","created_at":"2024-05-03 12:05:25","updated_at":"2024-05-03 12:05:25"},
    {"detail_id":"1338","order_id":"9e93f233-7bf7-4114-96f9-d7333eb42d47","product_id":"31","top":"-7","left":"25","z_index":"0","rotate":"0","created_at":"2024-05-03 12:05:25","updated_at":"2024-05-03 12:05:25"},
    {"detail_id":"1339","order_id":"9e93f233-7bf7-4114-96f9-d7333eb42d47","product_id":"30","top":"1","left":"130","z_index":"0","rotate":"0","created_at":"2024-05-03 12:05:25","updated_at":"2024-05-03 12:05:25"},
    {"detail_id":"1340","order_id":"9e93f233-7bf7-4114-96f9-d7333eb42d47","product_id":"30","top":"0","left":"0","z_index":"0","rotate":"0","created_at":"2024-05-03 12:05:25","updated_at":"2024-05-03 12:05:25"},
    {"detail_id":"1341","order_id":"48fb3265-4a16-4fd3-9e6f-ae92b85a32e7","product_id":"2","top":"0","left":"0","z_index":"0","rotate":"0","created_at":"2024-05-03 12:09:02","updated_at":"2024-05-03 12:09:02"},
    {"detail_id":"1342","order_id":"48fb3265-4a16-4fd3-9e6f-ae92b85a32e7","product_id":"3","top":"0","left":"0","z_index":"0","rotate":"0","created_at":"2024-05-03 12:09:02","updated_at":"2024-05-03 12:09:02"},
    {"detail_id":"1343","order_id":"48fb3265-4a16-4fd3-9e6f-ae92b85a32e7","product_id":"4","top":"0","left":"0","z_index":"0","rotate":"0","created_at":"2024-05-03 12:09:02","updated_at":"2024-05-03 12:09:02"},
    {"detail_id":"1344","order_id":"48fb3265-4a16-4fd3-9e6f-ae92b85a32e7","product_id":"2","top":"0","left":"0","z_index":"0","rotate":"0","created_at":"2024-05-03 12:09:02","updated_at":"2024-05-03 12:09:02"},
    {"detail_id":"1345","order_id":"48fb3265-4a16-4fd3-9e6f-ae92b85a32e7","product_id":"3","top":"0","left":"0","z_index":"0","rotate":"0","created_at":"2024-05-03 12:09:02","updated_at":"2024-05-03 12:09:02"},
    {"detail_id":"1346","order_id":"48fb3265-4a16-4fd3-9e6f-ae92b85a32e7","product_id":"4","top":"0","left":"0","z_index":"0","rotate":"0","created_at":"2024-05-03 12:09:02","updated_at":"2024-05-03 12:09:02"},
    {"detail_id":"1347","order_id":"48fb3265-4a16-4fd3-9e6f-ae92b85a32e7","product_id":"31","top":"0","left":"0","z_index":"0","rotate":"0","created_at":"2024-05-03 12:09:02","updated_at":"2024-05-03 12:09:02"},
    {"detail_id":"1348","order_id":"48fb3265-4a16-4fd3-9e6f-ae92b85a32e7","product_id":"31","top":"-7","left":"25","z_index":"0","rotate":"0","created_at":"2024-05-03 12:09:02","updated_at":"2024-05-03 12:09:02"},
    {"detail_id":"1349","order_id":"48fb3265-4a16-4fd3-9e6f-ae92b85a32e7","product_id":"30","top":"1","left":"130","z_index":"0","rotate":"0","created_at":"2024-05-03 12:09:02","updated_at":"2024-05-03 12:09:02"},
    {"detail_id":"1350","order_id":"48fb3265-4a16-4fd3-9e6f-ae92b85a32e7","product_id":"30","top":"0","left":"0","z_index":"0","rotate":"0","created_at":"2024-05-03 12:09:02","updated_at":"2024-05-03 12:09:02"},
    {"detail_id":"1351","order_id":"3e50efcc-ab7d-43cb-928f-6e8796fd6e2c","product_id":"2","top":"0","left":"0","z_index":"0","rotate":"0","created_at":"2024-05-03 12:11:52","updated_at":"2024-05-03 12:11:52"},
    {"detail_id":"1352","order_id":"3e50efcc-ab7d-43cb-928f-6e8796fd6e2c","product_id":"3","top":"0","left":"0","z_index":"0","rotate":"0","created_at":"2024-05-03 12:11:52","updated_at":"2024-05-03 12:11:52"},
    {"detail_id":"1353","order_id":"3e50efcc-ab7d-43cb-928f-6e8796fd6e2c","product_id":"4","top":"0","left":"0","z_index":"0","rotate":"0","created_at":"2024-05-03 12:11:52","updated_at":"2024-05-03 12:11:52"},
    {"detail_id":"1354","order_id":"3e50efcc-ab7d-43cb-928f-6e8796fd6e2c","product_id":"2","top":"0","left":"0","z_index":"0","rotate":"0","created_at":"2024-05-03 12:11:52","updated_at":"2024-05-03 12:11:52"},
    {"detail_id":"1355","order_id":"3e50efcc-ab7d-43cb-928f-6e8796fd6e2c","product_id":"3","top":"0","left":"0","z_index":"0","rotate":"0","created_at":"2024-05-03 12:11:52","updated_at":"2024-05-03 12:11:52"},
    {"detail_id":"1356","order_id":"3e50efcc-ab7d-43cb-928f-6e8796fd6e2c","product_id":"4","top":"0","left":"0","z_index":"0","rotate":"0","created_at":"2024-05-03 12:11:52","updated_at":"2024-05-03 12:11:52"},
    {"detail_id":"1357","order_id":"3e50efcc-ab7d-43cb-928f-6e8796fd6e2c","product_id":"31","top":"0","left":"0","z_index":"0","rotate":"0","created_at":"2024-05-03 12:11:52","updated_at":"2024-05-03 12:11:52"},
    {"detail_id":"1358","order_id":"3e50efcc-ab7d-43cb-928f-6e8796fd6e2c","product_id":"31","top":"-7","left":"25","z_index":"0","rotate":"0","created_at":"2024-05-03 12:11:52","updated_at":"2024-05-03 12:11:52"},
    {"detail_id":"1359","order_id":"3e50efcc-ab7d-43cb-928f-6e8796fd6e2c","product_id":"30","top":"1","left":"130","z_index":"0","rotate":"0","created_at":"2024-05-03 12:11:52","updated_at":"2024-05-03 12:11:52"},
    {"detail_id":"1360","order_id":"3e50efcc-ab7d-43cb-928f-6e8796fd6e2c","product_id":"30","top":"0","left":"0","z_index":"0","rotate":"0","created_at":"2024-05-03 12:11:52","updated_at":"2024-05-03 12:11:52"},
    {"detail_id":"1361","order_id":"7b54cdfc-918b-43ff-9ebe-408918752e81","product_id":"36","top":"0","left":"10","z_index":"0","rotate":"0","created_at":"2024-05-05 17:19:00","updated_at":"2024-05-05 17:19:00"},
    {"detail_id":"1362","order_id":"7b54cdfc-918b-43ff-9ebe-408918752e81","product_id":"38","top":"0","left":"0","z_index":"0","rotate":"0","created_at":"2024-05-05 17:19:00","updated_at":"2024-05-05 17:19:00"},
    {"detail_id":"1363","order_id":"7b54cdfc-918b-43ff-9ebe-408918752e81","product_id":"43","top":"0","left":"4","z_index":"0","rotate":"0","created_at":"2024-05-05 17:19:00","updated_at":"2024-05-05 17:19:00"},
    {"detail_id":"1364","order_id":"7b54cdfc-918b-43ff-9ebe-408918752e81","product_id":"47","top":"0","left":"18","z_index":"0","rotate":"0","created_at":"2024-05-05 17:19:00","updated_at":"2024-05-05 17:19:00"},
    {"detail_id":"1365","order_id":"7b54cdfc-918b-43ff-9ebe-408918752e81","product_id":"36","top":"0","left":"10","z_index":"0","rotate":"0","created_at":"2024-05-05 17:19:00","updated_at":"2024-05-05 17:19:00"},
    {"detail_id":"1366","order_id":"7b54cdfc-918b-43ff-9ebe-408918752e81","product_id":"38","top":"0","left":"0","z_index":"0","rotate":"0","created_at":"2024-05-05 17:19:00","updated_at":"2024-05-05 17:19:00"},
    {"detail_id":"1367","order_id":"7b54cdfc-918b-43ff-9ebe-408918752e81","product_id":"43","top":"0","left":"4","z_index":"0","rotate":"0","created_at":"2024-05-05 17:19:00","updated_at":"2024-05-05 17:19:00"},
    {"detail_id":"1368","order_id":"7b54cdfc-918b-43ff-9ebe-408918752e81","product_id":"47","top":"0","left":"18","z_index":"0","rotate":"0","created_at":"2024-05-05 17:19:00","updated_at":"2024-05-05 17:19:00"},
    {"detail_id":"1369","order_id":"7b54cdfc-918b-43ff-9ebe-408918752e81","product_id":"36","top":"0","left":"10","z_index":"0","rotate":"0","created_at":"2024-05-05 17:19:00","updated_at":"2024-05-05 17:19:00"},
    {"detail_id":"1370","order_id":"7b54cdfc-918b-43ff-9ebe-408918752e81","product_id":"38","top":"0","left":"0","z_index":"0","rotate":"0","created_at":"2024-05-05 17:19:00","updated_at":"2024-05-05 17:19:00"},
    {"detail_id":"1371","order_id":"7b54cdfc-918b-43ff-9ebe-408918752e81","product_id":"43","top":"0","left":"4","z_index":"0","rotate":"0","created_at":"2024-05-05 17:19:00","updated_at":"2024-05-05 17:19:00"},
    {"detail_id":"1372","order_id":"7b54cdfc-918b-43ff-9ebe-408918752e81","product_id":"47","top":"0","left":"18","z_index":"0","rotate":"0","created_at":"2024-05-05 17:19:00","updated_at":"2024-05-05 17:19:00"},
    {"detail_id":"1373","order_id":"7b54cdfc-918b-43ff-9ebe-408918752e81","product_id":"36","top":"13","left":"9","z_index":"0","rotate":"0","created_at":"2024-05-05 17:19:00","updated_at":"2024-05-05 17:19:00"},
    {"detail_id":"1374","order_id":"7b54cdfc-918b-43ff-9ebe-408918752e81","product_id":"36","top":"6","left":"-41","z_index":"0","rotate":"0","created_at":"2024-05-05 17:19:00","updated_at":"2024-05-05 17:19:00"},
    {"detail_id":"1375","order_id":"7b54cdfc-918b-43ff-9ebe-408918752e81","product_id":"36","top":"4","left":"-81","z_index":"0","rotate":"0","created_at":"2024-05-05 17:19:00","updated_at":"2024-05-05 17:19:00"},
    {"detail_id":"1376","order_id":"7b54cdfc-918b-43ff-9ebe-408918752e81","product_id":"36","top":"0","left":"10","z_index":"0","rotate":"0","created_at":"2024-05-05 17:19:00","updated_at":"2024-05-05 17:19:00"},
    {"detail_id":"1377","order_id":"7b54cdfc-918b-43ff-9ebe-408918752e81","product_id":"38","top":"0","left":"0","z_index":"0","rotate":"0","created_at":"2024-05-05 17:19:00","updated_at":"2024-05-05 17:19:00"},
    {"detail_id":"1378","order_id":"7b54cdfc-918b-43ff-9ebe-408918752e81","product_id":"43","top":"0","left":"4","z_index":"0","rotate":"0","created_at":"2024-05-05 17:19:00","updated_at":"2024-05-05 17:19:00"},
    {"detail_id":"1379","order_id":"7b54cdfc-918b-43ff-9ebe-408918752e81","product_id":"47","top":"0","left":"18","z_index":"0","rotate":"0","created_at":"2024-05-05 17:19:00","updated_at":"2024-05-05 17:19:00"},
    {"detail_id":"1380","order_id":"7b54cdfc-918b-43ff-9ebe-408918752e81","product_id":"36","top":"0","left":"10","z_index":"0","rotate":"0","created_at":"2024-05-05 17:19:00","updated_at":"2024-05-05 17:19:00"},
    {"detail_id":"1381","order_id":"7b54cdfc-918b-43ff-9ebe-408918752e81","product_id":"38","top":"0","left":"0","z_index":"0","rotate":"0","created_at":"2024-05-05 17:19:00","updated_at":"2024-05-05 17:19:00"},
    {"detail_id":"1382","order_id":"7b54cdfc-918b-43ff-9ebe-408918752e81","product_id":"43","top":"0","left":"4","z_index":"0","rotate":"0","created_at":"2024-05-05 17:19:00","updated_at":"2024-05-05 17:19:00"},
    {"detail_id":"1383","order_id":"7b54cdfc-918b-43ff-9ebe-408918752e81","product_id":"47","top":"0","left":"18","z_index":"0","rotate":"0","created_at":"2024-05-05 17:19:00","updated_at":"2024-05-05 17:19:00"},
    {"detail_id":"1384","order_id":"7b54cdfc-918b-43ff-9ebe-408918752e81","product_id":"36","top":"0","left":"10","z_index":"0","rotate":"0","created_at":"2024-05-05 17:19:00","updated_at":"2024-05-05 17:19:00"},
    {"detail_id":"1385","order_id":"7b54cdfc-918b-43ff-9ebe-408918752e81","product_id":"38","top":"0","left":"0","z_index":"0","rotate":"0","created_at":"2024-05-05 17:19:00","updated_at":"2024-05-05 17:19:00"},
    {"detail_id":"1386","order_id":"7b54cdfc-918b-43ff-9ebe-408918752e81","product_id":"43","top":"0","left":"4","z_index":"0","rotate":"0","created_at":"2024-05-05 17:19:00","updated_at":"2024-05-05 17:19:00"},
    {"detail_id":"1387","order_id":"7b54cdfc-918b-43ff-9ebe-408918752e81","product_id":"47","top":"0","left":"18","z_index":"0","rotate":"0","created_at":"2024-05-05 17:19:00","updated_at":"2024-05-05 17:19:00"},
    {"detail_id":"1388","order_id":"7b54cdfc-918b-43ff-9ebe-408918752e81","product_id":"36","top":"0","left":"10","z_index":"0","rotate":"0","created_at":"2024-05-05 17:19:00","updated_at":"2024-05-05 17:19:00"},
    {"detail_id":"1389","order_id":"7b54cdfc-918b-43ff-9ebe-408918752e81","product_id":"38","top":"0","left":"0","z_index":"0","rotate":"0","created_at":"2024-05-05 17:19:00","updated_at":"2024-05-05 17:19:00"},
    {"detail_id":"1390","order_id":"7b54cdfc-918b-43ff-9ebe-408918752e81","product_id":"43","top":"0","left":"4","z_index":"0","rotate":"0","created_at":"2024-05-05 17:19:00","updated_at":"2024-05-05 17:19:00"},
    {"detail_id":"1391","order_id":"7b54cdfc-918b-43ff-9ebe-408918752e81","product_id":"47","top":"0","left":"18","z_index":"0","rotate":"0","created_at":"2024-05-05 17:19:00","updated_at":"2024-05-05 17:19:00"},
    {"detail_id":"1392","order_id":"7b54cdfc-918b-43ff-9ebe-408918752e81","product_id":"36","top":"13","left":"9","z_index":"0","rotate":"0","created_at":"2024-05-05 17:19:00","updated_at":"2024-05-05 17:19:00"},
    {"detail_id":"1393","order_id":"7b54cdfc-918b-43ff-9ebe-408918752e81","product_id":"36","top":"6","left":"-41","z_index":"0","rotate":"0","created_at":"2024-05-05 17:19:00","updated_at":"2024-05-05 17:19:00"},
    {"detail_id":"1394","order_id":"7b54cdfc-918b-43ff-9ebe-408918752e81","product_id":"36","top":"4","left":"-81","z_index":"0","rotate":"0","created_at":"2024-05-05 17:19:00","updated_at":"2024-05-05 17:19:00"},
    {"detail_id":"1395","order_id":"7b54cdfc-918b-43ff-9ebe-408918752e81","product_id":"36","top":"0","left":"10","z_index":"0","rotate":"0","created_at":"2024-05-05 17:19:00","updated_at":"2024-05-05 17:19:00"},
    {"detail_id":"1396","order_id":"7b54cdfc-918b-43ff-9ebe-408918752e81","product_id":"38","top":"33","left":"67","z_index":"0","rotate":"0","created_at":"2024-05-05 17:19:00","updated_at":"2024-05-05 17:19:00"},
    {"detail_id":"1397","order_id":"7b54cdfc-918b-43ff-9ebe-408918752e81","product_id":"43","top":"10","left":"-119","z_index":"0","rotate":"0","created_at":"2024-05-05 17:19:00","updated_at":"2024-05-05 17:19:00"},
    {"detail_id":"1398","order_id":"7b54cdfc-918b-43ff-9ebe-408918752e81","product_id":"47","top":"30","left":"117","z_index":"0","rotate":"0","created_at":"2024-05-05 17:19:00","updated_at":"2024-05-05 17:19:00"},
    {"detail_id":"1399","order_id":"7b54cdfc-918b-43ff-9ebe-408918752e81","product_id":"119","top":"13","left":"-74","z_index":"0","rotate":"0","created_at":"2024-05-05 17:19:00","updated_at":"2024-05-05 17:19:00"},
    {"detail_id":"1400","order_id":"7a55d16d-04a6-4429-a482-8b4f76840c52","product_id":"36","top":"0","left":"10","z_index":"0","rotate":"0","created_at":"2024-05-06 08:56:31","updated_at":"2024-05-06 08:56:31"},
    {"detail_id":"1401","order_id":"7a55d16d-04a6-4429-a482-8b4f76840c52","product_id":"38","top":"0","left":"0","z_index":"0","rotate":"0","created_at":"2024-05-06 08:56:31","updated_at":"2024-05-06 08:56:31"},
    {"detail_id":"1402","order_id":"7a55d16d-04a6-4429-a482-8b4f76840c52","product_id":"43","top":"0","left":"4","z_index":"0","rotate":"0","created_at":"2024-05-06 08:56:31","updated_at":"2024-05-06 08:56:31"},
    {"detail_id":"1403","order_id":"7a55d16d-04a6-4429-a482-8b4f76840c52","product_id":"47","top":"0","left":"18","z_index":"0","rotate":"0","created_at":"2024-05-06 08:56:31","updated_at":"2024-05-06 08:56:31"},
    {"detail_id":"1404","order_id":"f161be36-b39e-4b73-93f2-6edc73664d6b","product_id":"36","top":"0","left":"10","z_index":"0","rotate":"0","created_at":"2024-05-06 17:07:00","updated_at":"2024-05-06 17:07:00"},
    {"detail_id":"1405","order_id":"f161be36-b39e-4b73-93f2-6edc73664d6b","product_id":"38","top":"0","left":"0","z_index":"0","rotate":"0","created_at":"2024-05-06 17:07:00","updated_at":"2024-05-06 17:07:00"},
    {"detail_id":"1406","order_id":"f161be36-b39e-4b73-93f2-6edc73664d6b","product_id":"43","top":"0","left":"4","z_index":"0","rotate":"0","created_at":"2024-05-06 17:07:00","updated_at":"2024-05-06 17:07:00"},
    {"detail_id":"1407","order_id":"f161be36-b39e-4b73-93f2-6edc73664d6b","product_id":"47","top":"30","left":"3","z_index":"0","rotate":"0","created_at":"2024-05-06 17:07:00","updated_at":"2024-05-06 17:07:00"},
    {"detail_id":"1408","order_id":"f161be36-b39e-4b73-93f2-6edc73664d6b","product_id":"36","top":"15","left":"88","z_index":"0","rotate":"0","created_at":"2024-05-06 17:07:00","updated_at":"2024-05-06 17:07:00"},
    {"detail_id":"1409","order_id":"f161be36-b39e-4b73-93f2-6edc73664d6b","product_id":"38","top":"-45","left":"-44","z_index":"0","rotate":"0","created_at":"2024-05-06 17:07:00","updated_at":"2024-05-06 17:07:00"},
    {"detail_id":"1410","order_id":"f161be36-b39e-4b73-93f2-6edc73664d6b","product_id":"43","top":"20","left":"138","z_index":"0","rotate":"0","created_at":"2024-05-06 17:07:00","updated_at":"2024-05-06 17:07:00"},
    {"detail_id":"1411","order_id":"f161be36-b39e-4b73-93f2-6edc73664d6b","product_id":"47","top":"76","left":"-11","z_index":"0","rotate":"0","created_at":"2024-05-06 17:07:00","updated_at":"2024-05-06 17:07:00"},
    {"detail_id":"1412","order_id":"f161be36-b39e-4b73-93f2-6edc73664d6b","product_id":"36","top":"46","left":"-52","z_index":"0","rotate":"0","created_at":"2024-05-06 17:07:00","updated_at":"2024-05-06 17:07:00"},
    {"detail_id":"1413","order_id":"f161be36-b39e-4b73-93f2-6edc73664d6b","product_id":"38","top":"10","left":"-105","z_index":"0","rotate":"0","created_at":"2024-05-06 17:07:00","updated_at":"2024-05-06 17:07:00"},
    {"detail_id":"1414","order_id":"f161be36-b39e-4b73-93f2-6edc73664d6b","product_id":"43","top":"81","left":"54","z_index":"0","rotate":"0","created_at":"2024-05-06 17:07:00","updated_at":"2024-05-06 17:07:00"},
    {"detail_id":"1415","order_id":"f161be36-b39e-4b73-93f2-6edc73664d6b","product_id":"47","top":"61","left":"135","z_index":"0","rotate":"0","created_at":"2024-05-06 17:07:00","updated_at":"2024-05-06 17:07:00"},
    {"detail_id":"1416","order_id":"f161be36-b39e-4b73-93f2-6edc73664d6b","product_id":"113","top":"0","left":"79","z_index":"0","rotate":"0","created_at":"2024-05-06 17:07:00","updated_at":"2024-05-06 17:07:00"},
    {"detail_id":"1417","order_id":"f161be36-b39e-4b73-93f2-6edc73664d6b","product_id":"55","top":"84","left":"-2","z_index":"0","rotate":"0","created_at":"2024-05-06 17:07:00","updated_at":"2024-05-06 17:07:00"},
    {"detail_id":"1418","order_id":"f161be36-b39e-4b73-93f2-6edc73664d6b","product_id":"85","top":"72","left":"59","z_index":"0","rotate":"0","created_at":"2024-05-06 17:07:00","updated_at":"2024-05-06 17:07:00"},
    {"detail_id":"1419","order_id":"4a1dffbb-7e04-450d-9ba4-fa6f9b3a8ed0","product_id":"49","top":"46","left":"78","z_index":"0","rotate":"0","created_at":"2024-05-06 19:46:47","updated_at":"2024-05-06 19:46:47"},
    {"detail_id":"1420","order_id":"4a1dffbb-7e04-450d-9ba4-fa6f9b3a8ed0","product_id":"74","top":"59","left":"14","z_index":"0","rotate":"0","created_at":"2024-05-06 19:46:47","updated_at":"2024-05-06 19:46:47"}
    ]