[
  {
    "id": 1,
    "name": "孤挺花-紅",
    "product_image_flowers_id": 1,
    "product_category_id": 4,
    "share_color_id": 1,
    "price": 30,
    "stock": 100,
    "purchase_count": 27,
    "info": "花朵如燃燒的火焰，傳達著堅定的意志，象徵著不屈不撓的精神。",
    "store_id": 2,
    "size": "整體尺寸寬約5cm、高50cm(測量誤差±2cm)",
    "note": "如果某些花材缺貨，我們將以同價值或類似色系的花材代替。\n植物生長各有異，花瓣可能沒有對稱或完美無瑕，請注意這一點，完美主義者請慎思。\n如果您收到的花有嚴重損壞問題，請立即拍照並聯絡我們。如果判定為快遞公司的疏失，我們將補贈一枝花。\n鮮花不接受因花材喜好而退換貨，售出後不提供退換貨服務。根據消費者保護法第19條第2項但書規定，容易腐敗、保存期限較短或解約時即將逾期之商品，以及依照消費者要求所進行的客製化商品均不在退換貨服務的範圍內。",
    "overall_review": 5,
    "product_review_id": 1,
    "created_at": "2021/9/8 12:35",
    "updated_at": "2021/10/8 12:35"
  },
  {
    "id": 2,
    "name": "銀蓮花-紅",
    "product_image_flowers_id": 2,
    "product_category_id": 4,
    "share_color_id": 1,
    "price": 40,
    "stock": 200,
    "purchase_count": 143,
    "info": "柔美花瓣彷彿舞動的思念，蘊含著對未來的憧憬與無窮的期待。",
    "store_id": 3,
    "size": "整體尺寸寬約5cm、高50cm(測量誤差±2cm)",
    "note": "如果某些花材缺貨，我們將以同價值或類似色系的花材代替。\n植物生長各有異，花瓣可能沒有對稱或完美無瑕，請注意這一點，完美主義者請慎思。\n如果您收到的花有嚴重損壞問題，請立即拍照並聯絡我們。如果判定為快遞公司的疏失，我們將補贈一枝花。\n鮮花不接受因花材喜好而退換貨，售出後不提供退換貨服務。根據消費者保護法第19條第2項但書規定，容易腐敗、保存期限較短或解約時即將逾期之商品，以及依照消費者要求所進行的客製化商品均不在退換貨服務的範圍內。",
    "overall_review": 4,
    "product_review_id": 2,
    "created_at": "2020/12/29 18:22",
    "updated_at": "2021/1/29 18:22"
  },
  {
    "id": 3,
    "name": "蘋果花-白",
    "product_image_flowers_id": 3,
    "product_category_id": 4,
    "share_color_id": 11,
    "price": 50,
    "stock": 100,
    "purchase_count": 98,
    "info": "如春天的微風中綻放，象徵著智慧與充實的人生選擇。",
    "store_id": 4,
    "size": "整體尺寸寬約5cm、高50cm(測量誤差±2cm)",
    "note": "如果某些花材缺貨，我們將以同價值或類似色系的花材代替。\n植物生長各有異，花瓣可能沒有對稱或完美無瑕，請注意這一點，完美主義者請慎思。\n如果您收到的花有嚴重損壞問題，請立即拍照並聯絡我們。如果判定為快遞公司的疏失，我們將補贈一枝花。\n鮮花不接受因花材喜好而退換貨，售出後不提供退換貨服務。根據消費者保護法第19條第2項但書規定，容易腐敗、保存期限較短或解約時即將逾期之商品，以及依照消費者要求所進行的客製化商品均不在退換貨服務的範圍內。",
    "overall_review": 3,
    "product_review_id": 3,
    "created_at": "2023/4/10 08:57",
    "updated_at": "2023/5/10 08:57"
  },
  {
    "id": 4,
    "name": "紫菀-紫",
    "product_image_flowers_id": 4,
    "product_category_id": 4,
    "share_color_id": 6,
    "price": 30,
    "stock": 150,
    "purchase_count": 205,
    "info": "綻放的花束中散發著優雅，花朵細緻如星辰，教人感受到無盡的耐心。",
    "store_id": 5,
    "size": "整體尺寸寬約5cm、高50cm(測量誤差±2cm)",
    "note": "如果某些花材缺貨，我們將以同價值或類似色系的花材代替。\n植物生長各有異，花瓣可能沒有對稱或完美無瑕，請注意這一點，完美主義者請慎思。\n如果您收到的花有嚴重損壞問題，請立即拍照並聯絡我們。如果判定為快遞公司的疏失，我們將補贈一枝花。\n鮮花不接受因花材喜好而退換貨，售出後不提供退換貨服務。根據消費者保護法第19條第2項但書規定，容易腐敗、保存期限較短或解約時即將逾期之商品，以及依照消費者要求所進行的客製化商品均不在退換貨服務的範圍內。",
    "overall_review": 5,
    "product_review_id": 4,
    "created_at": "2024/3/17 21:40",
    "updated_at": "2024/4/17 21:40"
  },
  {
    "id": 5,
    "name": "風鈴草-藍",
    "product_image_flowers_id": 5,
    "product_category_id": 4,
    "share_color_id": 5,
    "price": 40,
    "stock": 200,
    "purchase_count": 63,
    "info": "柔軟花瓣如舞動長裙，表達對生命的感激，細緻的花朵彷彿悄悄說著謝意。",
    "store_id": 6,
    "size": "整體尺寸寬約5cm、高50cm(測量誤差±2cm)",
    "note": "如果某些花材缺貨，我們將以同價值或類似色系的花材代替。\n植物生長各有異，花瓣可能沒有對稱或完美無瑕，請注意這一點，完美主義者請慎思。\n如果您收到的花有嚴重損壞問題，請立即拍照並聯絡我們。如果判定為快遞公司的疏失，我們將補贈一枝花。\n鮮花不接受因花材喜好而退換貨，售出後不提供退換貨服務。根據消費者保護法第19條第2項但書規定，容易腐敗、保存期限較短或解約時即將逾期之商品，以及依照消費者要求所進行的客製化商品均不在退換貨服務的範圍內。",
    "overall_review": 4,
    "product_review_id": 5,
    "created_at": "2020/10/1 15:10",
    "updated_at": "2020/11/1 15:10"
  },
  {
    "id": 6,
    "name": "山茶花-紅",
    "product_image_flowers_id": 6,
    "product_category_id": 4,
    "share_color_id": 1,
    "price": 50,
    "stock": 100,
    "purchase_count": 276,
    "info": "簡約而高雅，花心如命運的轉折，綻放出深沉的美麗，寓意著人生的起承轉合。",
    "store_id": 7,
    "size": "整體尺寸寬約5cm、高50cm(測量誤差±2cm)",
    "note": "如果某些花材缺貨，我們將以同價值或類似色系的花材代替。\n植物生長各有異，花瓣可能沒有對稱或完美無瑕，請注意這一點，完美主義者請慎思。\n如果您收到的花有嚴重損壞問題，請立即拍照並聯絡我們。如果判定為快遞公司的疏失，我們將補贈一枝花。\n鮮花不接受因花材喜好而退換貨，售出後不提供退換貨服務。根據消費者保護法第19條第2項但書規定，容易腐敗、保存期限較短或解約時即將逾期之商品，以及依照消費者要求所進行的客製化商品均不在退換貨服務的範圍內。",
    "overall_review": 3,
    "product_review_id": 6,
    "created_at": "2022/5/19 06:48",
    "updated_at": "2022/6/19 06:48"
  },
  {
    "id": 7,
    "name": "鐵線蓮-藍",
    "product_image_flowers_id": 7,
    "product_category_id": 4,
    "share_color_id": 5,
    "price": 30,
    "stock": 150,
    "purchase_count": 184,
    "info": "纖細的花瓣交織著智慧之美，彷彿心靈的綻放，充滿思索與深沈。",
    "store_id": 8,
    "size": "整體尺寸寬約5cm、高50cm(測量誤差±2cm)",
    "note": "如果某些花材缺貨，我們將以同價值或類似色系的花材代替。\n植物生長各有異，花瓣可能沒有對稱或完美無瑕，請注意這一點，完美主義者請慎思。\n如果您收到的花有嚴重損壞問題，請立即拍照並聯絡我們。如果判定為快遞公司的疏失，我們將補贈一枝花。\n鮮花不接受因花材喜好而退換貨，售出後不提供退換貨服務。根據消費者保護法第19條第2項但書規定，容易腐敗、保存期限較短或解約時即將逾期之商品，以及依照消費者要求所進行的客製化商品均不在退換貨服務的範圍內。",
    "overall_review": 5,
    "product_review_id": 7,
    "created_at": "2023/7/26 09:15",
    "updated_at": "2023/8/26 09:15"
  },
  {
    "id": 8,
    "name": "金雞菊-黃",
    "product_image_flowers_id": 8,
    "product_category_id": 4,
    "share_color_id": 3,
    "price": 40,
    "stock": 300,
    "purchase_count": 54,
    "info": "花朵如陽光灑落，象徵著永恆的喜悅，給人正面積極的力量。",
    "store_id": 9,
    "size": "整體尺寸寬約5cm、高50cm(測量誤差±2cm)",
    "note": "如果某些花材缺貨，我們將以同價值或類似色系的花材代替。\n植物生長各有異，花瓣可能沒有對稱或完美無瑕，請注意這一點，完美主義者請慎思。\n如果您收到的花有嚴重損壞問題，請立即拍照並聯絡我們。如果判定為快遞公司的疏失，我們將補贈一枝花。\n鮮花不接受因花材喜好而退換貨，售出後不提供退換貨服務。根據消費者保護法第19條第2項但書規定，容易腐敗、保存期限較短或解約時即將逾期之商品，以及依照消費者要求所進行的客製化商品均不在退換貨服務的範圍內。",
    "overall_review": 4,
    "product_review_id": 8,
    "created_at": "2021/3/8 14:59",
    "updated_at": "2021/4/8 14:59"
  },
  {
    "id": 9,
    "name": "番紅花-紫",
    "product_image_flowers_id": 9,
    "product_category_id": 4,
    "share_color_id": 6,
    "price": 50,
    "stock": 200,
    "purchase_count": 217,
    "info": "冬天的盡頭迎來的第一抹顏色，象徵著歡喜和希望，為生命注入新的活力。",
    "store_id": 10,
    "size": "整體尺寸寬約5cm、高50cm(測量誤差±2cm)",
    "note": "如果某些花材缺貨，我們將以同價值或類似色系的花材代替。\n植物生長各有異，花瓣可能沒有對稱或完美無瑕，請注意這一點，完美主義者請慎思。\n如果您收到的花有嚴重損壞問題，請立即拍照並聯絡我們。如果判定為快遞公司的疏失，我們將補贈一枝花。\n鮮花不接受因花材喜好而退換貨，售出後不提供退換貨服務。根據消費者保護法第19條第2項但書規定，容易腐敗、保存期限較短或解約時即將逾期之商品，以及依照消費者要求所進行的客製化商品均不在退換貨服務的範圍內。",
    "overall_review": 3,
    "product_review_id": 9,
    "created_at": "2024/1/29 17:30",
    "updated_at": "2024/2/29 17:30"
  },
  {
    "id": 10,
    "name": "水仙花-黃",
    "product_image_flowers_id": 10,
    "product_category_id": 4,
    "share_color_id": 3,
    "price": 30,
    "stock": 150,
    "purchase_count": 291,
    "info": "瓶插的黃金花語，寓意著重生和嶄新的開始，為人生注入勇氣與希望。",
    "store_id": 11,
    "size": "整體尺寸寬約5cm、高50cm(測量誤差±2cm)",
    "note": "如果某些花材缺貨，我們將以同價值或類似色系的花材代替。\n植物生長各有異，花瓣可能沒有對稱或完美無瑕，請注意這一點，完美主義者請慎思。\n如果您收到的花有嚴重損壞問題，請立即拍照並聯絡我們。如果判定為快遞公司的疏失，我們將補贈一枝花。\n鮮花不接受因花材喜好而退換貨，售出後不提供退換貨服務。根據消費者保護法第19條第2項但書規定，容易腐敗、保存期限較短或解約時即將逾期之商品，以及依照消費者要求所進行的客製化商品均不在退換貨服務的範圍內。",
    "overall_review": 5,
    "product_review_id": 10,
    "created_at": "2023/11/6 11:27",
    "updated_at": "2023/12/6 11:27"
  },
  {
    "id": 11,
    "name": "大理花-紅",
    "product_image_flowers_id": 11,
    "product_category_id": 4,
    "share_color_id": 1,
    "price": 40,
    "stock": 100,
    "purchase_count": 112,
    "info": "豐盛的花瓣彷彿展現自尊的風采，散發著自信與堅持。",
    "store_id": 2,
    "size": "整體尺寸寬約5cm、高50cm(測量誤差±2cm)",
    "note": "如果某些花材缺貨，我們將以同價值或類似色系的花材代替。\n植物生長各有異，花瓣可能沒有對稱或完美無瑕，請注意這一點，完美主義者請慎思。\n如果您收到的花有嚴重損壞問題，請立即拍照並聯絡我們。如果判定為快遞公司的疏失，我們將補贈一枝花。\n鮮花不接受因花材喜好而退換貨，售出後不提供退換貨服務。根據消費者保護法第19條第2項但書規定，容易腐敗、保存期限較短或解約時即將逾期之商品，以及依照消費者要求所進行的客製化商品均不在退換貨服務的範圍內。",
    "overall_review": 4,
    "product_review_id": 11,
    "created_at": "2022/8/15 23:09",
    "updated_at": "2022/9/15 23:09"
  },
  {
    "id": 12,
    "name": "北美靛藍-藍",
    "product_image_flowers_id": 12,
    "product_category_id": 4,
    "share_color_id": 5,
    "price": 50,
    "stock": 200,
    "purchase_count": 7,
    "info": "5的花朵如同沉浸在深邃的夢境，象徵著靈感的啟發和直覺的力量。",
    "store_id": 3,
    "size": "整體尺寸寬約5cm、高50cm(測量誤差±2cm)",
    "note": "如果某些花材缺貨，我們將以同價值或類似色系的花材代替。\n植物生長各有異，花瓣可能沒有對稱或完美無瑕，請注意這一點，完美主義者請慎思。\n如果您收到的花有嚴重損壞問題，請立即拍照並聯絡我們。如果判定為快遞公司的疏失，我們將補贈一枝花。\n鮮花不接受因花材喜好而退換貨，售出後不提供退換貨服務。根據消費者保護法第19條第2項但書規定，容易腐敗、保存期限較短或解約時即將逾期之商品，以及依照消費者要求所進行的客製化商品均不在退換貨服務的範圍內。",
    "overall_review": 3,
    "product_review_id": 12,
    "created_at": "2020/7/11 07:40",
    "updated_at": "2020/8/11 07:40"
  },
  {
    "id": 13,
    "name": "勿忘我-藍",
    "product_image_flowers_id": 13,
    "product_category_id": 4,
    "share_color_id": 5,
    "price": 30,
    "stock": 300,
    "purchase_count": 159,
    "info": "小巧的花朵帶有深深的5，象徵著永恆不忘的記憶和真摯的感情。",
    "store_id": 4,
    "size": "整體尺寸寬約5cm、高50cm(測量誤差±2cm)",
    "note": "如果某些花材缺貨，我們將以同價值或類似色系的花材代替。\n植物生長各有異，花瓣可能沒有對稱或完美無瑕，請注意這一點，完美主義者請慎思。\n如果您收到的花有嚴重損壞問題，請立即拍照並聯絡我們。如果判定為快遞公司的疏失，我們將補贈一枝花。\n鮮花不接受因花材喜好而退換貨，售出後不提供退換貨服務。根據消費者保護法第19條第2項但書規定，容易腐敗、保存期限較短或解約時即將逾期之商品，以及依照消費者要求所進行的客製化商品均不在退換貨服務的範圍內。",
    "overall_review": 5,
    "product_review_id": 13,
    "created_at": "2021/6/27 19:55",
    "updated_at": "2021/7/27 19:55"
  },
  {
    "id": 14,
    "name": "香水草-紫",
    "product_image_flowers_id": 14,
    "product_category_id": 4,
    "share_color_id": 6,
    "price": 40,
    "stock": 250,
    "purchase_count": 236,
    "info": "花香四溢的香水草代表著對夢想的堅持與奉獻的精神。",
    "store_id": 5,
    "size": "整體尺寸寬約5cm、高50cm(測量誤差±2cm)",
    "note": "如果某些花材缺貨，我們將以同價值或類似色系的花材代替。\n植物生長各有異，花瓣可能沒有對稱或完美無瑕，請注意這一點，完美主義者請慎思。\n如果您收到的花有嚴重損壞問題，請立即拍照並聯絡我們。如果判定為快遞公司的疏失，我們將補贈一枝花。\n鮮花不接受因花材喜好而退換貨，售出後不提供退換貨服務。根據消費者保護法第19條第2項但書規定，容易腐敗、保存期限較短或解約時即將逾期之商品，以及依照消費者要求所進行的客製化商品均不在退換貨服務的範圍內。",
    "overall_review": 4,
    "product_review_id": 14,
    "created_at": "2024/4/28 10:25",
    "updated_at": "2024/5/28 10:25"
  },
  {
    "id": 15,
    "name": "非洲菊-白",
    "product_image_flowers_id": 15,
    "product_category_id": 4,
    "share_color_id": 11,
    "price": 50,
    "stock": 100,
    "purchase_count": 82,
    "info": "艷麗的花瓣展現出純潔歡喜的氛圍，彷彿充滿天真的童心。",
    "store_id": 6,
    "size": "整體尺寸寬約5cm、高50cm(測量誤差±2cm)",
    "note": "如果某些花材缺貨，我們將以同價值或類似色系的花材代替。\n植物生長各有異，花瓣可能沒有對稱或完美無瑕，請注意這一點，完美主義者請慎思。\n如果您收到的花有嚴重損壞問題，請立即拍照並聯絡我們。如果判定為快遞公司的疏失，我們將補贈一枝花。\n鮮花不接受因花材喜好而退換貨，售出後不提供退換貨服務。根據消費者保護法第19條第2項但書規定，容易腐敗、保存期限較短或解約時即將逾期之商品，以及依照消費者要求所進行的客製化商品均不在退換貨服務的範圍內。",
    "overall_review": 3,
    "product_review_id": 15,
    "created_at": "2023/12/21 04:14",
    "updated_at": "2024/1/21 04:14"
  },
  {
    "id": 16,
    "name": "唐菖蒲-粉",
    "product_image_flowers_id": 16,
    "product_category_id": 4,
    "share_color_id": 7,
    "price": 30,
    "stock": 100,
    "purchase_count": 295,
    "info": "高聳的花穗代表著性格的力量，象徵著道德正直與堅強。",
    "store_id": 7,
    "size": "整體尺寸寬約5cm、高50cm(測量誤差±2cm)",
    "note": "如果某些花材缺貨，我們將以同價值或類似色系的花材代替。\n植物生長各有異，花瓣可能沒有對稱或完美無瑕，請注意這一點，完美主義者請慎思。\n如果您收到的花有嚴重損壞問題，請立即拍照並聯絡我們。如果判定為快遞公司的疏失，我們將補贈一枝花。\n鮮花不接受因花材喜好而退換貨，售出後不提供退換貨服務。根據消費者保護法第19條第2項但書規定，容易腐敗、保存期限較短或解約時即將逾期之商品，以及依照消費者要求所進行的客製化商品均不在退換貨服務的範圍內。",
    "overall_review": 5,
    "product_review_id": 16,
    "created_at": "2020/8/18 22:13",
    "updated_at": "2020/9/18 22:13"
  },
  {
    "id": 17,
    "name": "大岩桐-紫",
    "product_image_flowers_id": 17,
    "product_category_id": 4,
    "share_color_id": 6,
    "price": 40,
    "stock": 200,
    "purchase_count": 193,
    "info": "華麗的花形展現出一見鍾情的美感，散發著自信與優雅。",
    "store_id": 8,
    "size": "整體尺寸寬約5cm、高50cm(測量誤差±2cm)",
    "note": "如果某些花材缺貨，我們將以同價值或類似色系的花材代替。\n植物生長各有異，花瓣可能沒有對稱或完美無瑕，請注意這一點，完美主義者請慎思。\n如果您收到的花有嚴重損壞問題，請立即拍照並聯絡我們。如果判定為快遞公司的疏失，我們將補贈一枝花。\n鮮花不接受因花材喜好而退換貨，售出後不提供退換貨服務。根據消費者保護法第19條第2項但書規定，容易腐敗、保存期限較短或解約時即將逾期之商品，以及依照消費者要求所進行的客製化商品均不在退換貨服務的範圍內。",
    "overall_review": 4,
    "product_review_id": 17,
    "created_at": "2022/2/10 03:28",
    "updated_at": "2022/3/10 03:28"
  },
  {
    "id": 18,
    "name": "朱槿花-紅",
    "product_image_flowers_id": 18,
    "product_category_id": 4,
    "share_color_id": 1,
    "price": 50,
    "stock": 100,
    "purchase_count": 40,
    "info": "艷紅的花瓣如夏日的陽光，象徵著美麗與幸福的生活。",
    "store_id": 9,
    "size": "整體尺寸寬約5cm、高50cm(測量誤差±2cm)",
    "note": "如果某些花材缺貨，我們將以同價值或類似色系的花材代替。\n植物生長各有異，花瓣可能沒有對稱或完美無瑕，請注意這一點，完美主義者請慎思。\n如果您收到的花有嚴重損壞問題，請立即拍照並聯絡我們。如果判定為快遞公司的疏失，我們將補贈一枝花。\n鮮花不接受因花材喜好而退換貨，售出後不提供退換貨服務。根據消費者保護法第19條第2項但書規定，容易腐敗、保存期限較短或解約時即將逾期之商品，以及依照消費者要求所進行的客製化商品均不在退換貨服務的範圍內。",
    "overall_review": 3,
    "product_review_id": 18,
    "created_at": "2021/1/16 13:49",
    "updated_at": "2021/2/16 13:49"
  },
  {
    "id": 19,
    "name": "金銀花-白",
    "product_image_flowers_id": 19,
    "product_category_id": 4,
    "share_color_id": 11,
    "price": 30,
    "stock": 150,
    "purchase_count": 279,
    "info": "芬芳的金銀花散發出家庭的幸福氛圍，象徵著情感的奉獻。",
    "store_id": 10,
    "size": "整體尺寸寬約5cm、高50cm(測量誤差±2cm)",
    "note": "如果某些花材缺貨，我們將以同價值或類似色系的花材代替。\n植物生長各有異，花瓣可能沒有對稱或完美無瑕，請注意這一點，完美主義者請慎思。\n如果您收到的花有嚴重損壞問題，請立即拍照並聯絡我們。如果判定為快遞公司的疏失，我們將補贈一枝花。\n鮮花不接受因花材喜好而退換貨，售出後不提供退換貨服務。根據消費者保護法第19條第2項但書規定，容易腐敗、保存期限較短或解約時即將逾期之商品，以及依照消費者要求所進行的客製化商品均不在退換貨服務的範圍內。",
    "overall_review": 2,
    "product_review_id": 19,
    "created_at": "2023/3/5 16:20",
    "updated_at": "2023/4/5 16:20"
  },
  {
    "id": 20,
    "name": "風信子-紅",
    "product_image_flowers_id": 20,
    "product_category_id": 4,
    "share_color_id": 1,
    "price": 40,
    "stock": 200,
    "purchase_count": 123,
    "info": "多彩的風信子花瓣彷彿是一場春日的遊戲，帶來歡樂與輕松的氛圍。",
    "store_id": 11,
    "size": "整體尺寸寬約5cm、高50cm(測量誤差±2cm)",
    "note": "如果某些花材缺貨，我們將以同價值或類似色系的花材代替。\n植物生長各有異，花瓣可能沒有對稱或完美無瑕，請注意這一點，完美主義者請慎思。\n如果您收到的花有嚴重損壞問題，請立即拍照並聯絡我們。如果判定為快遞公司的疏失，我們將補贈一枝花。\n鮮花不接受因花材喜好而退換貨，售出後不提供退換貨服務。根據消費者保護法第19條第2項但書規定，容易腐敗、保存期限較短或解約時即將逾期之商品，以及依照消費者要求所進行的客製化商品均不在退換貨服務的範圍內。",
    "overall_review": 1,
    "product_review_id": 20,
    "created_at": "2020/9/14 05:37",
    "updated_at": "2020/10/14 05:37"
  },
  {
    "id": 21,
    "name": "繡球花-粉",
    "product_image_flowers_id": 21,
    "product_category_id": 4,
    "share_color_id": 7,
    "price": 50,
    "stock": 100,
    "purchase_count": 209,
    "info": "繁複的花球如感激之心綻放，象徵著理解和感激的情感。",
    "store_id": 2,
    "size": "整體尺寸寬約5cm、高50cm(測量誤差±2cm)",
    "note": "如果某些花材缺貨，我們將以同價值或類似色系的花材代替。\n植物生長各有異，花瓣可能沒有對稱或完美無瑕，請注意這一點，完美主義者請慎思。\n如果您收到的花有嚴重損壞問題，請立即拍照並聯絡我們。如果判定為快遞公司的疏失，我們將補贈一枝花。\n鮮花不接受因花材喜好而退換貨，售出後不提供退換貨服務。根據消費者保護法第19條第2項但書規定，容易腐敗、保存期限較短或解約時即將逾期之商品，以及依照消費者要求所進行的客製化商品均不在退換貨服務的範圍內。",
    "overall_review": 5,
    "product_review_id": 21,
    "created_at": "2024/2/17 20:07",
    "updated_at": "2024/3/17 20:07"
  },
  {
    "id": 22,
    "name": "鳶尾花-紫",
    "product_image_flowers_id": 22,
    "product_category_id": 4,
    "share_color_id": 6,
    "price": 30,
    "stock": 150,
    "purchase_count": 77,
    "info": "鳶尾花瓣猶如彩虹，傳達著美好的訊息和祝福。",
    "store_id": 3,
    "size": "整體尺寸寬約5cm、高50cm(測量誤差±2cm)",
    "note": "如果某些花材缺貨，我們將以同價值或類似色系的花材代替。\n植物生長各有異，花瓣可能沒有對稱或完美無瑕，請注意這一點，完美主義者請慎思。\n如果您收到的花有嚴重損壞問題，請立即拍照並聯絡我們。如果判定為快遞公司的疏失，我們將補贈一枝花。\n鮮花不接受因花材喜好而退換貨，售出後不提供退換貨服務。根據消費者保護法第19條第2項但書規定，容易腐敗、保存期限較短或解約時即將逾期之商品，以及依照消費者要求所進行的客製化商品均不在退換貨服務的範圍內。",
    "overall_review": 4,
    "product_review_id": 22,
    "created_at": "2022/7/4 08:33",
    "updated_at": "2022/8/4 08:33"
  },
  {
    "id": 23,
    "name": "紫丁香-紫",
    "product_image_flowers_id": 23,
    "product_category_id": 4,
    "share_color_id": 6,
    "price": 40,
    "stock": 300,
    "purchase_count": 258,
    "info": "芬芳的紫丁香散發著愛的初感動，帶來浪漫的氛圍。",
    "store_id": 4,
    "size": "整體尺寸寬約5cm、高50cm(測量誤差±2cm)",
    "note": "如果某些花材缺貨，我們將以同價值或類似色系的花材代替。\n植物生長各有異，花瓣可能沒有對稱或完美無瑕，請注意這一點，完美主義者請慎思。\n如果您收到的花有嚴重損壞問題，請立即拍照並聯絡我們。如果判定為快遞公司的疏失，我們將補贈一枝花。\n鮮花不接受因花材喜好而退換貨，售出後不提供退換貨服務。根據消費者保護法第19條第2項但書規定，容易腐敗、保存期限較短或解約時即將逾期之商品，以及依照消費者要求所進行的客製化商品均不在退換貨服務的範圍內。",
    "overall_review": 3,
    "product_review_id": 23,
    "created_at": "2021/4/26 00:58",
    "updated_at": "2021/5/26 00:58"
  },
  {
    "id": 24,
    "name": "百合花-白",
    "product_image_flowers_id": 24,
    "product_category_id": 4,
    "share_color_id": 11,
    "price": 50,
    "stock": 200,
    "purchase_count": 32,
    "info": "高雅的百合花象徵著威嚴和美德，展現出高貴的氛圍。",
    "store_id": 5,
    "size": "整體尺寸寬約5cm、高50cm(測量誤差±2cm)",
    "note": "如果某些花材缺貨，我們將以同價值或類似色系的花材代替。\n植物生長各有異，花瓣可能沒有對稱或完美無瑕，請注意這一點，完美主義者請慎思。\n如果您收到的花有嚴重損壞問題，請立即拍照並聯絡我們。如果判定為快遞公司的疏失，我們將補贈一枝花。\n鮮花不接受因花材喜好而退換貨，售出後不提供退換貨服務。根據消費者保護法第19條第2項但書規定，容易腐敗、保存期限較短或解約時即將逾期之商品，以及依照消費者要求所進行的客製化商品均不在退換貨服務的範圍內。",
    "overall_review": 5,
    "product_review_id": 24,
    "created_at": "2023/6/10 19:46",
    "updated_at": "2023/7/10 19:46"
  },
  {
    "id": 25,
    "name": "玉蘭花-白",
    "product_image_flowers_id": 25,
    "product_category_id": 4,
    "share_color_id": 11,
    "price": 30,
    "stock": 150,
    "purchase_count": 281,
    "info": "華麗的玉蘭花代表著高貴和自尊，散發出迷人的氛圍。",
    "store_id": 6,
    "size": "整體尺寸寬約5cm、高50cm(測量誤差±2cm)",
    "note": "如果某些花材缺貨，我們將以同價值或類似色系的花材代替。\n植物生長各有異，花瓣可能沒有對稱或完美無瑕，請注意這一點，完美主義者請慎思。\n如果您收到的花有嚴重損壞問題，請立即拍照並聯絡我們。如果判定為快遞公司的疏失，我們將補贈一枝花。\n鮮花不接受因花材喜好而退換貨，售出後不提供退換貨服務。根據消費者保護法第19條第2項但書規定，容易腐敗、保存期限較短或解約時即將逾期之商品，以及依照消費者要求所進行的客製化商品均不在退換貨服務的範圍內。",
    "overall_review": 4,
    "product_review_id": 25,
    "created_at": "2020/11/22 11:29",
    "updated_at": "2020/12/22 11:29"
  },
  {
    "id": 26,
    "name": "牽牛花-紫",
    "product_image_flowers_id": 26,
    "product_category_id": 4,
    "share_color_id": 6,
    "price": 40,
    "stock": 100,
    "purchase_count": 67,
    "info": "早晨綻放的牽牛花象徵著情感和堅定的決心，帶來愉悅的感覺。",
    "store_id": 7,
    "size": "整體尺寸寬約5cm、高50cm(測量誤差±2cm)",
    "note": "如果某些花材缺貨，我們將以同價值或類似色系的花材代替。\n植物生長各有異，花瓣可能沒有對稱或完美無瑕，請注意這一點，完美主義者請慎思。\n如果您收到的花有嚴重損壞問題，請立即拍照並聯絡我們。如果判定為快遞公司的疏失，我們將補贈一枝花。\n鮮花不接受因花材喜好而退換貨，售出後不提供退換貨服務。根據消費者保護法第19條第2項但書規定，容易腐敗、保存期限較短或解約時即將逾期之商品，以及依照消費者要求所進行的客製化商品均不在退換貨服務的範圍內。",
    "overall_review": 3,
    "product_review_id": 26,
    "created_at": "2022/9/2 02:15",
    "updated_at": "2022/10/2 02:15"
  },
  {
    "id": 27,
    "name": "旱金蓮-紅",
    "product_image_flowers_id": 27,
    "product_category_id": 4,
    "share_color_id": 1,
    "price": 50,
    "stock": 200,
    "purchase_count": 15,
    "info": "火1的旱金蓮代表成功與征服，散發著積極的能量。",
    "store_id": 8,
    "size": "整體尺寸寬約5cm、高50cm(測量誤差±2cm)",
    "note": "如果某些花材缺貨，我們將以同價值或類似色系的花材代替。\n植物生長各有異，花瓣可能沒有對稱或完美無瑕，請注意這一點，完美主義者請慎思。\n如果您收到的花有嚴重損壞問題，請立即拍照並聯絡我們。如果判定為快遞公司的疏失，我們將補贈一枝花。\n鮮花不接受因花材喜好而退換貨，售出後不提供退換貨服務。根據消費者保護法第19條第2項但書規定，容易腐敗、保存期限較短或解約時即將逾期之商品，以及依照消費者要求所進行的客製化商品均不在退換貨服務的範圍內。",
    "overall_review": 5,
    "product_review_id": 27,
    "created_at": "2021/5/30 23:21",
    "updated_at": "2021/6/30 23:21"
  },
  {
    "id": 28,
    "name": "三色堇-紫",
    "product_image_flowers_id": 28,
    "product_category_id": 4,
    "share_color_id": 6,
    "price": 30,
    "stock": 300,
    "purchase_count": 178,
    "info": "彩色的三色堇猶如甜美的想法，帶來愉悅和輕鬆的心情。",
    "store_id": 9,
    "size": "整體尺寸寬約5cm、高50cm(測量誤差±2cm)",
    "note": "如果某些花材缺貨，我們將以同價值或類似色系的花材代替。\n植物生長各有異，花瓣可能沒有對稱或完美無瑕，請注意這一點，完美主義者請慎思。\n如果您收到的花有嚴重損壞問題，請立即拍照並聯絡我們。如果判定為快遞公司的疏失，我們將補贈一枝花。\n鮮花不接受因花材喜好而退換貨，售出後不提供退換貨服務。根據消費者保護法第19條第2項但書規定，容易腐敗、保存期限較短或解約時即將逾期之商品，以及依照消費者要求所進行的客製化商品均不在退換貨服務的範圍內。",
    "overall_review": 4,
    "product_review_id": 28,
    "created_at": "2024/5/5 14:42",
    "updated_at": "2024/6/5 14:42"
  },
  {
    "id": 29,
    "name": "芍藥-粉",
    "product_image_flowers_id": 29,
    "product_category_id": 4,
    "share_color_id": 7,
    "price": 40,
    "stock": 250,
    "purchase_count": 245,
    "info": "豐盈的芍藥花象徵著豐盛和慈悲，綻放出華麗的氛圍。",
    "store_id": 10,
    "size": "整體尺寸寬約5cm、高50cm(測量誤差±2cm)",
    "note": "如果某些花材缺貨，我們將以同價值或類似色系的花材代替。\n植物生長各有異，花瓣可能沒有對稱或完美無瑕，請注意這一點，完美主義者請慎思。\n如果您收到的花有嚴重損壞問題，請立即拍照並聯絡我們。如果判定為快遞公司的疏失，我們將補贈一枝花。\n鮮花不接受因花材喜好而退換貨，售出後不提供退換貨服務。根據消費者保護法第19條第2項但書規定，容易腐敗、保存期限較短或解約時即將逾期之商品，以及依照消費者要求所進行的客製化商品均不在退換貨服務的範圍內。",
    "overall_review": 3,
    "product_review_id": 29,
    "created_at": "2020/12/2 06:39",
    "updated_at": "2020/1/2 06:39"
  },
  {
    "id": 30,
    "name": "天藍繡球-紫",
    "product_image_flowers_id": 30,
    "product_category_id": 4,
    "share_color_id": 6,
    "price": 50,
    "stock": 100,
    "purchase_count": 2,
    "info": "多彩的天藍繡球花形成和諧的花球，象徵著和睦與團結。",
    "store_id": 11,
    "size": "整體尺寸寬約5cm、高50cm(測量誤差±2cm)",
    "note": "如果某些花材缺貨，我們將以同價值或類似色系的花材代替。\n植物生長各有異，花瓣可能沒有對稱或完美無瑕，請注意這一點，完美主義者請慎思。\n如果您收到的花有嚴重損壞問題，請立即拍照並聯絡我們。如果判定為快遞公司的疏失，我們將補贈一枝花。\n鮮花不接受因花材喜好而退換貨，售出後不提供退換貨服務。根據消費者保護法第19條第2項但書規定，容易腐敗、保存期限較短或解約時即將逾期之商品，以及依照消費者要求所進行的客製化商品均不在退換貨服務的範圍內。",
    "overall_review": 5,
    "product_review_id": 30,
    "created_at": "2023/1/19 08:05",
    "updated_at": "2023/2/19 08:05"
  },
  {
    "id": 31,
    "name": "報春花-紫",
    "product_image_flowers_id": 31,
    "product_category_id": 4,
    "share_color_id": 6,
    "price": 30,
    "stock": 100,
    "purchase_count": 188,
    "info": "報春花花語表達著年輕的愛，猶如春天的陽光，充滿希望與活力。",
    "store_id": 2,
    "size": "整體尺寸寬約5cm、高50cm(測量誤差±2cm)",
    "note": "如果某些花材缺貨，我們將以同價值或類似色系的花材代替。\n植物生長各有異，花瓣可能沒有對稱或完美無瑕，請注意這一點，完美主義者請慎思。\n如果您收到的花有嚴重損壞問題，請立即拍照並聯絡我們。如果判定為快遞公司的疏失，我們將補贈一枝花。\n鮮花不接受因花材喜好而退換貨，售出後不提供退換貨服務。根據消費者保護法第19條第2項但書規定，容易腐敗、保存期限較短或解約時即將逾期之商品，以及依照消費者要求所進行的客製化商品均不在退換貨服務的範圍內。",
    "overall_review": 4,
    "product_review_id": 31,
    "created_at": "2021/8/21 17:56",
    "updated_at": "2021/9/21 17:56"
  },
  {
    "id": 32,
    "name": "玫瑰花-粉",
    "product_image_flowers_id": 32,
    "product_category_id": 4,
    "share_color_id": 7,
    "price": 40,
    "stock": 200,
    "purchase_count": 296,
    "info": "玫瑰花是愛情的象徵，花瓣如愛戀的心靈，彰顯濃濃的浪漫氛圍。",
    "store_id": 3,
    "size": "整體尺寸寬約5cm、高50cm(測量誤差±2cm)",
    "note": "如果某些花材缺貨，我們將以同價值或類似色系的花材代替。\n植物生長各有異，花瓣可能沒有對稱或完美無瑕，請注意這一點，完美主義者請慎思。\n如果您收到的花有嚴重損壞問題，請立即拍照並聯絡我們。如果判定為快遞公司的疏失，我們將補贈一枝花。\n鮮花不接受因花材喜好而退換貨，售出後不提供退換貨服務。根據消費者保護法第19條第2項但書規定，容易腐敗、保存期限較短或解約時即將逾期之商品，以及依照消費者要求所進行的客製化商品均不在退換貨服務的範圍內。",
    "overall_review": 3,
    "product_review_id": 32,
    "created_at": "2022/4/5 12:49",
    "updated_at": "2022/5/5 12:49"
  },
  {
    "id": 33,
    "name": "玫瑰花-紅",
    "product_image_flowers_id": 33,
    "product_category_id": 4,
    "share_color_id": 1,
    "price": 50,
    "stock": 100,
    "purchase_count": 92,
    "info": "神秘的紅玫瑰彷彿蘊藏著無盡的故事，讓人忍不住想要探尋其中的奧秘。",
    "store_id": 4,
    "size": "整體尺寸寬約5cm、高50cm(測量誤差±2cm)",
    "note": "如果某些花材缺貨，我們將以同價值或類似色系的花材代替。\n植物生長各有異，花瓣可能沒有對稱或完美無瑕，請注意這一點，完美主義者請慎思。\n如果您收到的花有嚴重損壞問題，請立即拍照並聯絡我們。如果判定為快遞公司的疏失，我們將補贈一枝花。\n鮮花不接受因花材喜好而退換貨，售出後不提供退換貨服務。根據消費者保護法第19條第2項但書規定，容易腐敗、保存期限較短或解約時即將逾期之商品，以及依照消費者要求所進行的客製化商品均不在退換貨服務的範圍內。",
    "overall_review": 5,
    "product_review_id": 33,
    "created_at": "2020/6/13 18:17",
    "updated_at": "2020/7/13 18:17"
  },
  {
    "id": 34,
    "name": "玫瑰花-白",
    "product_image_flowers_id": 34,
    "product_category_id": 4,
    "share_color_id": 11,
    "price": 30,
    "stock": 150,
    "purchase_count": 129,
    "info": "花瓣潔白無瑕，象徵著嶄新的起點與智慧，為未來的道路帶來啟示。",
    "store_id": 5,
    "size": "整體尺寸寬約5cm、高50cm(測量誤差±2cm)",
    "note": "如果某些花材缺貨，我們將以同價值或類似色系的花材代替。\n植物生長各有異，花瓣可能沒有對稱或完美無瑕，請注意這一點，完美主義者請慎思。\n如果您收到的花有嚴重損壞問題，請立即拍照並聯絡我們。如果判定為快遞公司的疏失，我們將補贈一枝花。\n鮮花不接受因花材喜好而退換貨，售出後不提供退換貨服務。根據消費者保護法第19條第2項但書規定，容易腐敗、保存期限較短或解約時即將逾期之商品，以及依照消費者要求所進行的客製化商品均不在退換貨服務的範圍內。",
    "overall_review": 4,
    "product_review_id": 34,
    "created_at": "2024/3/1 04:30",
    "updated_at": "2024/4/1 04:30"
  },
  {
    "id": 35,
    "name": "玫瑰花-黃",
    "product_image_flowers_id": 35,
    "product_category_id": 4,
    "share_color_id": 3,
    "price": 40,
    "stock": 200,
    "purchase_count": 217,
    "info": "花瓣如陽光般明亮溫暖、熱情奔放，如真摯而持久的友誼，帶來溫馨與歡樂。",
    "store_id": 6,
    "size": "整體尺寸寬約5cm、高50cm(測量誤差±2cm)",
    "note": "如果某些花材缺貨，我們將以同價值或類似色系的花材代替。\n植物生長各有異，花瓣可能沒有對稱或完美無瑕，請注意這一點，完美主義者請慎思。\n如果您收到的花有嚴重損壞問題，請立即拍照並聯絡我們。如果判定為快遞公司的疏失，我們將補贈一枝花。\n鮮花不接受因花材喜好而退換貨，售出後不提供退換貨服務。根據消費者保護法第19條第2項但書規定，容易腐敗、保存期限較短或解約時即將逾期之商品，以及依照消費者要求所進行的客製化商品均不在退換貨服務的範圍內。",
    "overall_review": 3,
    "product_review_id": 35,
    "created_at": "2023/10/18 09:10",
    "updated_at": "2023/11/18 09:10"
  },
  {
    "id": 36,
    "name": "藍睡蓮-藍",
    "product_image_flowers_id": 36,
    "product_category_id": 4,
    "share_color_id": 5,
    "price": 50,
    "stock": 100,
    "purchase_count": 173,
    "info": "藍睡蓮代表著心靈的開悟，花瓣展開如心靈的智慧與寧靜。",
    "store_id": 7,
    "size": "整體尺寸寬約5cm、高50cm(測量誤差±2cm)",
    "note": "如果某些花材缺貨，我們將以同價值或類似色系的花材代替。\n植物生長各有異，花瓣可能沒有對稱或完美無瑕，請注意這一點，完美主義者請慎思。\n如果您收到的花有嚴重損壞問題，請立即拍照並聯絡我們。如果判定為快遞公司的疏失，我們將補贈一枝花。\n鮮花不接受因花材喜好而退換貨，售出後不提供退換貨服務。根據消費者保護法第19條第2項但書規定，容易腐敗、保存期限較短或解約時即將逾期之商品，以及依照消費者要求所進行的客製化商品均不在退換貨服務的範圍內。",
    "overall_review": 5,
    "product_review_id": 36,
    "created_at": "2021/2/23 21:28",
    "updated_at": "2021/3/23 21:28"
  },
  {
    "id": 37,
    "name": "金魚草-紅",
    "product_image_flowers_id": 37,
    "product_category_id": 4,
    "share_color_id": 1,
    "price": 30,
    "stock": 150,
    "purchase_count": 65,
    "info": "金魚草花語象徵著仁慈和善心，花形狀如金魚，給人溫暖與關懷。",
    "store_id": 8,
    "size": "整體尺寸寬約5cm、高50cm(測量誤差±2cm)",
    "note": "如果某些花材缺貨，我們將以同價值或類似色系的花材代替。\n植物生長各有異，花瓣可能沒有對稱或完美無瑕，請注意這一點，完美主義者請慎思。\n如果您收到的花有嚴重損壞問題，請立即拍照並聯絡我們。如果判定為快遞公司的疏失，我們將補贈一枝花。\n鮮花不接受因花材喜好而退換貨，售出後不提供退換貨服務。根據消費者保護法第19條第2項但書規定，容易腐敗、保存期限較短或解約時即將逾期之商品，以及依照消費者要求所進行的客製化商品均不在退換貨服務的範圍內。",
    "overall_review": 4,
    "product_review_id": 37,
    "created_at": "2022/12/7 13:54",
    "updated_at": "2023/1/7 13:54"
  },
  {
    "id": 38,
    "name": "香碗豆-粉",
    "product_image_flowers_id": 38,
    "product_category_id": 4,
    "share_color_id": 7,
    "price": 40,
    "stock": 300,
    "purchase_count": 201,
    "info": "香碗豆花代表著極樂的情感，芬芳的香氣帶來愉悅的心情。",
    "store_id": 9,
    "size": "整體尺寸寬約5cm、高50cm(測量誤差±2cm)",
    "note": "如果某些花材缺貨，我們將以同價值或類似色系的花材代替。\n植物生長各有異，花瓣可能沒有對稱或完美無瑕，請注意這一點，完美主義者請慎思。\n如果您收到的花有嚴重損壞問題，請立即拍照並聯絡我們。如果判定為快遞公司的疏失，我們將補贈一枝花。\n鮮花不接受因花材喜好而退換貨，售出後不提供退換貨服務。根據消費者保護法第19條第2項但書規定，容易腐敗、保存期限較短或解約時即將逾期之商品，以及依照消費者要求所進行的客製化商品均不在退換貨服務的範圍內。",
    "overall_review": 3,
    "product_review_id": 38,
    "created_at": "2020/4/9 10:52",
    "updated_at": "2020/5/9 10:52"
  },
  {
    "id": 39,
    "name": "西洋石竹-紅",
    "product_image_flowers_id": 39,
    "product_category_id": 4,
    "share_color_id": 1,
    "price": 50,
    "stock": 200,
    "purchase_count": 113,
    "info": "西洋石竹花語表達著英勇與微笑的美好，象徵著積極向前的生活態度。",
    "store_id": 10,
    "size": "整體尺寸寬約5cm、高50cm(測量誤差±2cm)",
    "note": "如果某些花材缺貨，我們將以同價值或類似色系的花材代替。\n植物生長各有異，花瓣可能沒有對稱或完美無瑕，請注意這一點，完美主義者請慎思。\n如果您收到的花有嚴重損壞問題，請立即拍照並聯絡我們。如果判定為快遞公司的疏失，我們將補贈一枝花。\n鮮花不接受因花材喜好而退換貨，售出後不提供退換貨服務。根據消費者保護法第19條第2項但書規定，容易腐敗、保存期限較短或解約時即將逾期之商品，以及依照消費者要求所進行的客製化商品均不在退換貨服務的範圍內。",
    "overall_review": 5,
    "product_review_id": 39,
    "created_at": "2024/1/23 07:15",
    "updated_at": "2024/2/23 07:15"
  },
  {
    "id": 40,
    "name": "矮龍膽-藍",
    "product_image_flowers_id": 40,
    "product_category_id": 4,
    "share_color_id": 5,
    "price": 30,
    "stock": 150,
    "purchase_count": 299,
    "info": "矮龍膽花代表著力量和療癒，花朵猶如吹響的號角，帶來正面的能量。",
    "store_id": 11,
    "size": "整體尺寸寬約5cm、高50cm(測量誤差±2cm)",
    "note": "如果某些花材缺貨，我們將以同價值或類似色系的花材代替。\n植物生長各有異，花瓣可能沒有對稱或完美無瑕，請注意這一點，完美主義者請慎思。\n如果您收到的花有嚴重損壞問題，請立即拍照並聯絡我們。如果判定為快遞公司的疏失，我們將補贈一枝花。\n鮮花不接受因花材喜好而退換貨，售出後不提供退換貨服務。根據消費者保護法第19條第2項但書規定，容易腐敗、保存期限較短或解約時即將逾期之商品，以及依照消費者要求所進行的客製化商品均不在退換貨服務的範圍內。",
    "overall_review": 4,
    "product_review_id": 40,
    "created_at": "2023/2/14 01:36",
    "updated_at": "2023/3/14 01:36"
  },
  {
    "id": 41,
    "name": "晚香玉-白",
    "product_image_flowers_id": 41,
    "product_category_id": 4,
    "share_color_id": 11,
    "price": 40,
    "stock": 100,
    "purchase_count": 39,
    "info": "晚香玉花語表達危險的愉悅，花香濃郁，散發著神秘的氛圍。",
    "store_id": 2,
    "size": "整體尺寸寬約5cm、高50cm(測量誤差±2cm)",
    "note": "如果某些花材缺貨，我們將以同價值或類似色系的花材代替。\n植物生長各有異，花瓣可能沒有對稱或完美無瑕，請注意這一點，完美主義者請慎思。\n如果您收到的花有嚴重損壞問題，請立即拍照並聯絡我們。如果判定為快遞公司的疏失，我們將補贈一枝花。\n鮮花不接受因花材喜好而退換貨，售出後不提供退換貨服務。根據消費者保護法第19條第2項但書規定，容易腐敗、保存期限較短或解約時即將逾期之商品，以及依照消費者要求所進行的客製化商品均不在退換貨服務的範圍內。",
    "overall_review": 3,
    "product_review_id": 41,
    "created_at": "2021/10/29 16:07",
    "updated_at": "2021/11/29 16:07"
  },
  {
    "id": 42,
    "name": "鬱金香-紅",
    "product_image_flowers_id": 42,
    "product_category_id": 4,
    "share_color_id": 1,
    "price": 50,
    "stock": 200,
    "purchase_count": 152,
    "info": "鬱金香花語象徵著友誼與感激，花型優雅，為特別的人帶來美好祝福。",
    "store_id": 3,
    "size": "整體尺寸寬約5cm、高50cm(測量誤差±2cm)",
    "note": "如果某些花材缺貨，我們將以同價值或類似色系的花材代替。\n植物生長各有異，花瓣可能沒有對稱或完美無瑕，請注意這一點，完美主義者請慎思。\n如果您收到的花有嚴重損壞問題，請立即拍照並聯絡我們。如果判定為快遞公司的疏失，我們將補贈一枝花。\n鮮花不接受因花材喜好而退換貨，售出後不提供退換貨服務。根據消費者保護法第19條第2項但書規定，容易腐敗、保存期限較短或解約時即將逾期之商品，以及依照消費者要求所進行的客製化商品均不在退換貨服務的範圍內。",
    "overall_review": 5,
    "product_review_id": 42,
    "created_at": "2022/11/26 05:20",
    "updated_at": "2022/12/26 05:20"
  },
  {
    "id": 43,
    "name": "香鈴草-白",
    "product_image_flowers_id": 43,
    "product_category_id": 4,
    "share_color_id": 11,
    "price": 30,
    "stock": 300,
    "purchase_count": 283,
    "info": "香鈴草花語表達著細緻而轉瞬即逝的美，彷彿是瞬間的幸福。",
    "store_id": 4,
    "size": "整體尺寸寬約5cm、高50cm(測量誤差±2cm)",
    "note": "如果某些花材缺貨，我們將以同價值或類似色系的花材代替。\n植物生長各有異，花瓣可能沒有對稱或完美無瑕，請注意這一點，完美主義者請慎思。\n如果您收到的花有嚴重損壞問題，請立即拍照並聯絡我們。如果判定為快遞公司的疏失，我們將補贈一枝花。\n鮮花不接受因花材喜好而退換貨，售出後不提供退換貨服務。根據消費者保護法第19條第2項但書規定，容易腐敗、保存期限較短或解約時即將逾期之商品，以及依照消費者要求所進行的客製化商品均不在退換貨服務的範圍內。",
    "overall_review": 4,
    "product_review_id": 43,
    "created_at": "2020/1/25 15:45",
    "updated_at": "2020/2/25 15:45"
  },
  {
    "id": 44,
    "name": "紫羅蘭-紫",
    "product_image_flowers_id": 44,
    "product_category_id": 4,
    "share_color_id": 6,
    "price": 20,
    "stock": 250,
    "purchase_count": 93,
    "info": "紫羅蘭花代表著信仰和中庸，小巧的花朵散發出清新的香氣，寓意著內在的寧靜。",
    "store_id": 5,
    "size": "整體尺寸寬約5cm、高50cm(測量誤差±2cm)",
    "note": "如果某些花材缺貨，我們將以同價值或類似色系的花材代替。\n植物生長各有異，花瓣可能沒有對稱或完美無瑕，請注意這一點，完美主義者請慎思。\n如果您收到的花有嚴重損壞問題，請立即拍照並聯絡我們。如果判定為快遞公司的疏失，我們將補贈一枝花。\n鮮花不接受因花材喜好而退換貨，售出後不提供退換貨服務。根據消費者保護法第19條第2項但書規定，容易腐敗、保存期限較短或解約時即將逾期之商品，以及依照消費者要求所進行的客製化商品均不在退換貨服務的範圍內。",
    "overall_review": 3,
    "product_review_id": 44,
    "created_at": "2020/8/10 03:49",
    "updated_at": "2020/9/10 03:49"
  }
]